sc_use_cases/__init__.py
sc_use_cases/siem/siem_uc_example.py
sc_use_cases-0.1.0.dist-info/WHEEL
sc_use_cases-0.1.0.dist-info/METADATA
sc_use_cases-0.1.0.dist-info/RECORD
