Metadata-Version: 2.1
Name: sc-use-cases
Version: 0.1.0
Summary: 
Author: Ross Bown
Author-email: rossbo@softcat.com
Requires-Python: >=3.6,<4.0
Classifier: Programming Language :: Python :: 3
Classifier: Programming Language :: Python :: 3.6
Classifier: Programming Language :: Python :: 3.7
Classifier: Programming Language :: Python :: 3.8
Classifier: Programming Language :: Python :: 3.9
Classifier: Programming Language :: Python :: 3.10
Classifier: Programming Language :: Python :: 3.11
Requires-Dist: pydantic (>=1.10,<2.0)
Requires-Dist: swimlane (>=10.9,<11.0)
